sg_logging/__init__.py
sg_logging/log.py
sg_logging-0.0.9.dist-info/LICENSE
sg_logging-0.0.9.dist-info/METADATA
sg_logging-0.0.9.dist-info/WHEEL
sg_logging-0.0.9.dist-info/top_level.txt
sg_logging-0.0.9.dist-info/RECORD
