Metadata-Version: 2.1
Name: sg-logging
Version: 0.0.9
Summary: Logging into Papertrail
Home-page: UNKNOWN
Author: Viral Communications
Author-email: viral-grads@media.mit.edu
License: UNKNOWN
Platform: UNKNOWN
Classifier: Programming Language :: Python :: 3
Classifier: License :: OSI Approved :: MIT License
Classifier: Operating System :: OS Independent
